thermoblock/__init__.py
thermoblock/resources/colorspectrum.jpg
thermoblock/resources/colorspectrum.pck
thermoblock/resources/materiallist.pck
thermoblock-23.7.0.dev2.dist-info/LICENSE
thermoblock-23.7.0.dev2.dist-info/METADATA
thermoblock-23.7.0.dev2.dist-info/WHEEL
thermoblock-23.7.0.dev2.dist-info/top_level.txt
thermoblock-23.7.0.dev2.dist-info/RECORD
